sbmlnetworkeditor/__init__.py
sbmlnetworkeditor/sbmlnetworkeditor.py
sbmlnetworkeditor-0.0.16.dist-info/LICENSE
sbmlnetworkeditor-0.0.16.dist-info/METADATA
sbmlnetworkeditor-0.0.16.dist-info/WHEEL
sbmlnetworkeditor-0.0.16.dist-info/top_level.txt
sbmlnetworkeditor-0.0.16.dist-info/RECORD
